Metadata-Version: 1.0
Name: nekobot
Version: 1.2
Summary: NekoBot API Python Wrapper
Home-page: https://github.com/hibikidesu/NekoBotAPI-py
Author: hibikidesu
Author-email: UNKNOWN
License: UNKNOWN
Keywords: nekobot api discord
Platform: UNKNOWN
